{
    "type": "RootItem",
    "uuid": "{46b1d56d-d96f-4050-a920-89df3caac831}",
    "children": [
        {
            "type": "SeperatorItem",
            "uuid": "{b9276ad5-416b-49b0-b996-72d923f2bea8}",
            "name": "Nodes",
            "children": [
                {
                    "type": "PropertyItem",
                    "uuid": "{374a07e8-558f-4357-b306-36837aa9fa40}",
                    "key": "Vector",
                    "value": "",
                    "children": [
                        {
                            "type": "IntegerPropertyItem",
                            "uuid": "{441b1ab9-4f36-4c9f-b185-48c82c10dc3a}",
                            "key": "X",
                            "value": 1
                        },
                        {
                            "type": "IntegerPropertyItem",
                            "uuid": "{04db752e-f148-41ba-85cd-e62168124f89}",
                            "key": "Y",
                            "value": 0
                        },
                        {
                            "type": "IntegerPropertyItem",
                            "uuid": "{95c52fb3-5468-4aec-8602-8ca84a7e6c66}",
                            "key": "Z",
                            "value": 0
                        }
                    ]
                }
            ]
        },
        {
            "type": "SeperatorItem",
            "uuid": "{852b10c6-5a36-42c5-954b-912721a941e5}",
            "name": "Edges"
        },
        {
            "type": "SeperatorItem",
            "uuid": "{cafad98e-9f00-4934-a433-3a2b51815634}",
            "name": "Frames"
        }
    ]
}