{
    "type": "RootItem",
    "uuid": "{55eec97a-0762-4c00-a89f-092a7a1510a3}",
    "children": [
        {
            "type": "SeperatorItem",
            "uuid": "{8b87e990-aac7-4e93-84d8-841a2e80e8a4}",
            "name": "Nodes",
            "children": [
                {
                    "type": "PropertyItem",
                    "uuid": "{df40da96-c7ca-475a-97ba-d2f5d522ca72}",
                    "key": "Vector",
                    "value": "",
                    "children": [
                        {
                            "type": "IntegerPropertyItem",
                            "uuid": "{c7024fa2-266e-4f0e-a805-f3d9bb44b4a8}",
                            "key": "X",
                            "value": 1
                        },
                        {
                            "type": "IntegerPropertyItem",
                            "uuid": "{7c53a540-e497-4262-bf9a-09ffe25cb229}",
                            "key": "Y",
                            "value": 0
                        },
                        {
                            "type": "IntegerPropertyItem",
                            "uuid": "{45cc1c0c-5143-4765-bcbe-b3bc2d8af5b5}",
                            "key": "Z",
                            "value": 0
                        }
                    ]
                }
            ]
        },
        {
            "type": "SeperatorItem",
            "uuid": "{e063f641-6480-40b0-a813-ddc080450130}",
            "name": "Edges"
        },
        {
            "type": "SeperatorItem",
            "uuid": "{595a9364-7d4c-4348-a694-d25b5c2d281a}",
            "name": "Frames"
        }
    ]
}